MANIFEST.in
README.rst
setup.py
scape/__init__.py
scape/__main__.py
scape.egg-info/PKG-INFO
scape.egg-info/SOURCES.txt
scape.egg-info/dependency_links.txt
scape.egg-info/top_level.txt
scape/command/__init__.py
scape/command/base.py
scape/command/init.py
scape/command/main.py
scape/command/run.py
scape/conf/__init__.py
scape/conf/settings.py
scape/core/__init__.py
scape/core/core.py
scape/core/executor.py
scape/core/inner_executor.py
scape/core/parser.py
scape/core/sensor.py
scape/event/__init__.py
scape/event/action.py
scape/event/event.py
scape/event/signal.py
scape/framework/__init__.py
scape/framework/dispatch.py
scape/framework/receive.py
scape/framework/recognize.py
scape/stream/__init__.py
scape/stream/stream.py
scape/template/main.py
scape/template/conf/__init__.py
scape/template/conf/settings.py
scape/template/conf/__pycache__/__init__.cpython-38.pyc
scape/template/conf/__pycache__/settings.cpython-38.pyc
scape/template/project_name/__init__.py
scape/template/project_name/__pycache__/__init__.cpython-38.pyc
scape/template/project_name/executors/__init__.py
scape/template/project_name/executors/hello_executor.py
scape/template/project_name/executors/__pycache__/__init__.cpython-38.pyc
scape/template/project_name/executors/__pycache__/hello_executor.cpython-38.pyc
scape/template/project_name/parsers/__init__.py
scape/template/project_name/parsers/hello_parser.py
scape/template/project_name/parsers/__pycache__/__init__.cpython-38.pyc
scape/template/project_name/parsers/__pycache__/hello_parser.cpython-38.pyc
scape/template/project_name/sensors/__init__.py
scape/template/project_name/sensors/base_sensor.py
scape/template/project_name/sensors/hello_sensor.py
scape/template/project_name/sensors/__pycache__/__init__.cpython-38.pyc
scape/template/project_name/sensors/__pycache__/base_sensor.cpython-38.pyc
scape/template/project_name/sensors/__pycache__/hello_sensor.cpython-38.pyc