Metadata-Version: 1.0
Name: scape
Version: 0.9.9
Summary: a framework for raspberry pi developing
Home-page: https://github.com/Plane-walker/scape
Author: Plane-walker
Author-email: a990990@163.com
License: MIT Licence
Keywords: pip,raspberry pi
Platform: any
